README.md
setup.py
_skbuild/linux-x86_64-3.8/cmake-install/texture_mapping/texture_mapping
texture_mapping/__init__.py
texture_mapping.egg-info/PKG-INFO
texture_mapping.egg-info/SOURCES.txt
texture_mapping.egg-info/dependency_links.txt
texture_mapping.egg-info/entry_points.txt
texture_mapping.egg-info/requires.txt
texture_mapping.egg-info/top_level.txt
texture_mapping/apps/__init__.py
texture_mapping/apps/mapping.py