Metadata-Version: 2.1
Name: texture-mapping
Version: 0.0.8
Summary: PCL Texture Mapping Wrapper of Python
Home-page: https://github.com/iory/texture-mapping
Author: iory
Author-email: ab.ioryz@gmail.com
License: MIT
Classifier: Development Status :: 5 - Production/Stable
Classifier: Intended Audience :: Developers
Classifier: Natural Language :: English
Classifier: License :: OSI Approved :: MIT License
Classifier: Programming Language :: Python
Classifier: Programming Language :: Python :: 2.7
Classifier: Programming Language :: Python :: 3.5
Classifier: Programming Language :: Python :: 3.6
Classifier: Programming Language :: Python :: 3.7
Classifier: Programming Language :: Python :: Implementation :: CPython
Requires-Dist: scikit-build
Requires-Dist: pillow
